axml/__init__.py
axml/main.py
axml/arsc/__init__.py
axml/arsc/parser.py
axml/arsc/printer.py
axml/axml/__init__.py
axml/axml/parser.py
axml/axml/printer.py
axml/helper/__init__.py
axml/helper/logging.py
axml/parser/__init__.py
axml/parser/stringblock.py
axml/resources/__init__.py
axml/resources/public.json
axml/resources/public.py
axml/resources/public.xml
axml/utils/__init__.py
axml/utils/constants.py
axml/utils/exceptions.py
axml/utils/formatters.py
axml-0.0.2.dist-info/licenses/LICENSE
axml-0.0.2.dist-info/METADATA
axml-0.0.2.dist-info/WHEEL
axml-0.0.2.dist-info/entry_points.txt
axml-0.0.2.dist-info/top_level.txt
axml-0.0.2.dist-info/RECORD
